py3x/__init__.py
py3x-0.0.1.dist-info/METADATA
py3x-0.0.1.dist-info/RECORD
py3x-0.0.1.dist-info/WHEEL
py3x-0.0.1.dist-info/top_level.txt
