Metadata-Version: 2.1
Name: py3x
Version: 0.0.1
Summary: python3 extension
Home-page: https://github.com/uedak/py3x
Author: uedak
Author-email: UNKNOWN
License: UNKNOWN
Platform: UNKNOWN
Classifier: Development Status :: 3 - Alpha
Classifier: License :: OSI Approved :: MIT License
Classifier: Programming Language :: Python :: 3.6
